CRYSTALpy/__init__.py
CRYSTALpy/adsorb.py
CRYSTALpy/calculate.py
CRYSTALpy/convert.py
CRYSTALpy/crystal_io.py
CRYSTALpy/execute.py
CRYSTALpy/plot.py
CRYSTALpy/thermodynamics.py
CRYSTALpy/unit_test.py
CRYSTALpy/units.py
CRYSTALpy/utils.py
CRYSTAL_code_py-2022.12.21.dist-info/LICENSE.txt
CRYSTAL_code_py-2022.12.21.dist-info/METADATA
CRYSTAL_code_py-2022.12.21.dist-info/WHEEL
CRYSTAL_code_py-2022.12.21.dist-info/top_level.txt
CRYSTAL_code_py-2022.12.21.dist-info/RECORD
